LICENSE
MANIFEST.in
README.md
VERSION
requirements.txt
setup.py
pyannote_onnx/__init__.py
pyannote_onnx/cli.py
pyannote_onnx/inference_session.py
pyannote_onnx/pyannote_onnx.py
pyannote_onnx.egg-info/PKG-INFO
pyannote_onnx.egg-info/SOURCES.txt
pyannote_onnx.egg-info/dependency_links.txt
pyannote_onnx.egg-info/entry_points.txt
pyannote_onnx.egg-info/requires.txt
pyannote_onnx.egg-info/top_level.txt