Metadata-Version: 2.1
Name: pyannote-onnx
Version: 0.1.1
Summary: Pyannote ONNX
Home-page: https://github.com/pengzhendong/pyannote-onnx
Author: Zhendong Peng
Author-email: pzd17@tsinghua.org.cn
License: UNKNOWN
Platform: UNKNOWN
Classifier: Programming Language :: Python :: 3
Classifier: Operating System :: OS Independent
Classifier: Topic :: Scientific/Engineering
License-File: LICENSE
